CHANGELOG.md
MANIFEST.in
README.md
setup.py
bin/gpseqc_compare
bin/gpseqc_estimate
gpseqc/__init__.py
gpseqc/bed.py
gpseqc/centrality.py
gpseqc/compare.py
gpseqc/cutsite_domain.py
gpseqc/stats.py
gpseqc.egg-info/PKG-INFO
gpseqc.egg-info/SOURCES.txt
gpseqc.egg-info/dependency_links.txt
gpseqc.egg-info/requires.txt
gpseqc.egg-info/top_level.txt
gpseqc/test/__init__.py
gpseqc/test/test_bed.py
gpseqc/test/test_centrality.py
gpseqc/test/test_compare.py
gpseqc/test/test_cutsite_domain.py