Metadata-Version: 2.1
Name: gpseqc
Version: 2.3.6
Summary: GPSeq-based centrality estimation.
Home-page: https://github.com/ggirelli/gpseqc
Author: Gabriele Girelli
Author-email: gabriele.girelli@scilifelab.se
License: MIT
Keywords: DNA biology cell centrality nucleus genome region bed
Platform: UNKNOWN
Classifier: Development Status :: 4 - Beta
Classifier: Intended Audience :: Science/Research
Classifier: Topic :: Scientific/Engineering :: Bio-Informatics
Classifier: License :: OSI Approved :: MIT License
Classifier: Programming Language :: Python :: 3 :: Only
